{
    "id": 466,
    "name": "RatBurger",
    "author": "Pixelo",
    "creators": [],
    "verifier": "Pixelo",
    "verification": "https://www.youtube.com/watch?v=eCifbChQmXk",
    "peak": 42,
    "percentToQualify": 100,
    "records": [
        {    
            "user": "evil",
            "link": "https://youtu.be/Zqusjl0X94U",
            "percent": 100,
            "hz": 240
        },
        {    
            "user": "ZorpikGMD",
            "link": "https://youtu.be/E8YK7rgM8F4",
            "percent": 100,
            "hz": 240
        },
        {    
            "user": "cinderrblock",
            "link": "https://youtu.be/P7_nEZ18n7s?t=2699",
            "percent": 100,
            "hz": 240
        },
        {    
            "user": "hayden",
            "link": "https://youtu.be/xk8B58TABok",
            "percent": 100,
            "hz": 360
        },
        {    
            "user": "Rin",
            "link": "https://youtu.be/CO7DWHorYms",
            "percent": 100,
            "hz": 240
        },
        {    
            "user": "deepstrider2",
            "link": "https://cdn.discordapp.com/attachments/946049906899046401/1282030970350075935/rat.mp4?ex=66de88a2&is=66dd3722&hm=4b7180917da1bfcdb5f58b8afa7347f650c5302a6e433026647359a35c8a6efd&",
            "percent": 100,
            "hz": 240
        }
    ]
}
